deepcalo/__init__.py
deepcalo/data_generator.py
deepcalo/model_components.py
deepcalo/model_container.py
deepcalo/submodels.py
deepcalo/utils.py
deepcalo/callbacks/SGDR_lr_schedule.py
deepcalo/callbacks/__init__.py
deepcalo/callbacks/cyclic_lr_schedule.py
deepcalo/callbacks/lr_finder.py
deepcalo/callbacks/model_checkpoint.py
deepcalo/callbacks/one_cycle_lr_schedule.py
deepcalo/layers/__init__.py
deepcalo/layers/bias_correct.py
deepcalo/layers/film.py
deepcalo/layers/pgauss.py
deepcalo/layers/switch_normalization.py
deepcalo-0.2.3.dist-info/LICENSE
deepcalo-0.2.3.dist-info/METADATA
deepcalo-0.2.3.dist-info/WHEEL
deepcalo-0.2.3.dist-info/top_level.txt
deepcalo-0.2.3.dist-info/RECORD
