Metadata-Version: 2.1
Name: deepcalo
Version: 0.2.3
Summary: Package for doing deep supervised learning on ATLAS data.
Home-page: https://gitlab.com/ffaye/deepcalo
Author: Frederik Faye
Author-email: frederikfaye@gmail.com
License: UNKNOWN
Platform: UNKNOWN
Classifier: Programming Language :: Python :: 3
Classifier: License :: OSI Approved :: Apache Software License
Classifier: Operating System :: OS Independent
Requires-Dist: numpy (>=1.15.4)
Requires-Dist: keras (>=2.2.4)
Requires-Dist: h5py (>=2.8.0)
Requires-Dist: joblib (>=0.13.0)
Requires-Dist: keras-drop-block (>=0.4.0)
